{
  "displayName": "Markdown Preview Enhanced with litvis",
  "description": "Fork of markdown-preview-enhanced with added https://www.gicentre.net/litvis",
  "markdown-preview-enhanced-with-litvis.openPreviewToTheSide.title": "Markdown Preview Enhanced with litvis: Open Preview to the Side",
  "markdown-preview-enhanced-with-litvis.openPreview.title": "Markdown Preview Enhanced with litvis: Open Preview",
  "markdown-preview-enhanced-with-litvis.toggleScrollSync.title": "Markdown Preview Enhanced with litvis: Toggle Scroll Sync",
  "markdown-preview-enhanced-with-litvis.toggleLiveUpdate.title": "Markdown Preview Enhanced with litvis: Toggle Live Update",
  "markdown-preview-enhanced-with-litvis.toggleBreakOnSingleNewLine.title": "Markdown Preview Enhanced with litvis: Toggle Break On Single New Line",
  "markdown-preview-enhanced-with-litvis.openImageHelper.title": "Markdown Preview Enhanced with litvis: Image Helper",
  "markdown-preview-enhanced-with-litvis.runAllCodeChunks.title": "Markdown Preview Enhanced with litvis: Run All Code Chunks",
  "markdown-preview-enhanced-with-litvis.runCodeChunk.title": "Markdown Preview Enhanced with litvis: Run Code Chunk",
  "markdown-preview-enhanced-with-litvis.syncPreview.title": "Markdown Preview Enhanced with litvis: Sync Preview",
  "markdown-preview-enhanced-with-litvis.customizeCss.title": "Markdown Preview Enhanced with litvis: Customize CSS",
  "markdown-preview-enhanced-with-litvis.insertNewSlide.title": "Markdown Preview Enhanced with litvis: Insert New Slide",
  "markdown-preview-enhanced-with-litvis.insertTable.title": "Markdown Preview Enhanced with litvis: Insert Table",
  "markdown-preview-enhanced-with-litvis.insertPagebreak.title": "Markdown Preview Enhanced with litvis: Insert Page Break",
  "markdown-preview-enhanced-with-litvis.createTOC.title": "Markdown Preview Enhanced with litvis: Create TOC",
  "markdown-preview-enhanced-with-litvis.openMermaidConfig.title": "Markdown Preview Enhanced with litvis: Open Mermaid Config",
  "markdown-preview-enhanced-with-litvis.openMathJaxConfig.title": "Markdown Preview Enhanced with litvis: Open MathJax Config",
  "markdown-preview-enhanced-with-litvis.openKaTeXConfig.title": "Markdown Preview Enhanced with litvis: Open KaTeX Config",
  "markdown-preview-enhanced-with-litvis.extendParser.title": "Markdown Preview Enhanced with litvis: Extend Parser",
  "markdown-preview-enhanced-with-litvis.showUploadedImages.title": "Markdown Preview Enhanced with litvis: Show Uploaded Images",
  "markdown-preview-enhanced-with-litvis.clearCache.title": "Markdown Preview Enhanced with litvis: Clear Cache"
}
